{
  "formatVersion": 1,
  "database": {
    "version": 4,
    "identityHash": "2d709ab1dff06d0c8193ccd413a3d2b9",
    "entities": [
      {
        "tableName": "mood_entries",
        "createSql": "CREATE TABLE IF NOT EXISTS `${TABLE_NAME}` (`id` INTEGER PRIMARY KEY AUTOINCREMENT NOT NULL, `dateTime` INTEGER NOT NULL, `moodLevel` INTEGER NOT NULL, `note` TEXT NOT NULL)",
        "fields": [
          {
            "fieldPath": "id",
            "columnName": "id",
            "affinity": "INTEGER",
            "notNull": true
          },
          {
            "fieldPath": "dateTime",
            "columnName": "dateTime",
            "affinity": "INTEGER",
            "notNull": true
          },
          {
            "fieldPath": "moodLevel",
            "columnName": "moodLevel",
            "affinity": "INTEGER",
            "notNull": true
          },
          {
            "fieldPath": "note",
            "columnName": "note",
            "affinity": "TEXT",
            "notNull": true
          }
        ],
        "primaryKey": {
          "autoGenerate": true,
          "columnNames": [
            "id"
          ]
        },
        "indices": [],
        "foreignKeys": []
      },
      {
        "tableName": "activities",
        "createSql": "CREATE TABLE IF NOT EXISTS `${TABLE_NAME}` (`id` INTEGER PRIMARY KEY AUTOINCREMENT NOT NULL, `name` TEXT NOT NULL, `iconKey` TEXT NOT NULL, `sortOrder` INTEGER NOT NULL, `archived` INTEGER NOT NULL)",
        "fields": [
          {
            "fieldPath": "id",
            "columnName": "id",
            "affinity": "INTEGER",
            "notNull": true
          },
          {
            "fieldPath": "name",
            "columnName": "name",
            "affinity": "TEXT",
            "notNull": true
          },
          {
            "fieldPath": "iconKey",
            "columnName": "iconKey",
            "affinity": "TEXT",
            "notNull": true
          },
          {
            "fieldPath": "sortOrder",
            "columnName": "sortOrder",
            "affinity": "INTEGER",
            "notNull": true
          },
          {
            "fieldPath": "archived",
            "columnName": "archived",
            "affinity": "INTEGER",
            "notNull": true
          }
        ],
        "primaryKey": {
          "autoGenerate": true,
          "columnNames": [
            "id"
          ]
        },
        "indices": [],
        "foreignKeys": []
      },
      {
        "tableName": "entry_activity",
        "createSql": "CREATE TABLE IF NOT EXISTS `${TABLE_NAME}` (`entryId` INTEGER NOT NULL, `activityId` INTEGER NOT NULL, PRIMARY KEY(`entryId`, `activityId`))",
        "fields": [
          {
            "fieldPath": "entryId",
            "columnName": "entryId",
            "affinity": "INTEGER",
            "notNull": true
          },
          {
            "fieldPath": "activityId",
            "columnName": "activityId",
            "affinity": "INTEGER",
            "notNull": true
          }
        ],
        "primaryKey": {
          "autoGenerate": false,
          "columnNames": [
            "entryId",
            "activityId"
          ]
        },
        "indices": [
          {
            "name": "index_entry_activity_activityId",
            "unique": false,
            "columnNames": [
              "activityId"
            ],
            "orders": [],
            "createSql": "CREATE INDEX IF NOT EXISTS `index_entry_activity_activityId` ON `${TABLE_NAME}` (`activityId`)"
          }
        ],
        "foreignKeys": []
      },
      {
        "tableName": "journal_entries",
        "createSql": "CREATE TABLE IF NOT EXISTS `${TABLE_NAME}` (`id` INTEGER PRIMARY KEY AUTOINCREMENT NOT NULL, `dateTime` INTEGER NOT NULL, `title` TEXT NOT NULL, `body` TEXT NOT NULL)",
        "fields": [
          {
            "fieldPath": "id",
            "columnName": "id",
            "affinity": "INTEGER",
            "notNull": true
          },
          {
            "fieldPath": "dateTime",
            "columnName": "dateTime",
            "affinity": "INTEGER",
            "notNull": true
          },
          {
            "fieldPath": "title",
            "columnName": "title",
            "affinity": "TEXT",
            "notNull": true
          },
          {
            "fieldPath": "body",
            "columnName": "body",
            "affinity": "TEXT",
            "notNull": true
          }
        ],
        "primaryKey": {
          "autoGenerate": true,
          "columnNames": [
            "id"
          ]
        },
        "indices": [
          {
            "name": "index_journal_entries_dateTime",
            "unique": false,
            "columnNames": [
              "dateTime"
            ],
            "orders": [],
            "createSql": "CREATE INDEX IF NOT EXISTS `index_journal_entries_dateTime` ON `${TABLE_NAME}` (`dateTime`)"
          }
        ],
        "foreignKeys": []
      },
      {
        "tableName": "goals",
        "createSql": "CREATE TABLE IF NOT EXISTS `${TABLE_NAME}` (`id` INTEGER PRIMARY KEY AUTOINCREMENT NOT NULL, `title` TEXT NOT NULL, `activityId` INTEGER, `targetPerWeek` INTEGER NOT NULL, `createdAt` INTEGER NOT NULL, `archived` INTEGER NOT NULL)",
        "fields": [
          {
            "fieldPath": "id",
            "columnName": "id",
            "affinity": "INTEGER",
            "notNull": true
          },
          {
            "fieldPath": "title",
            "columnName": "title",
            "affinity": "TEXT",
            "notNull": true
          },
          {
            "fieldPath": "activityId",
            "columnName": "activityId",
            "affinity": "INTEGER",
            "notNull": false
          },
          {
            "fieldPath": "targetPerWeek",
            "columnName": "targetPerWeek",
            "affinity": "INTEGER",
            "notNull": true
          },
          {
            "fieldPath": "createdAt",
            "columnName": "createdAt",
            "affinity": "INTEGER",
            "notNull": true
          },
          {
            "fieldPath": "archived",
            "columnName": "archived",
            "affinity": "INTEGER",
            "notNull": true
          }
        ],
        "primaryKey": {
          "autoGenerate": true,
          "columnNames": [
            "id"
          ]
        },
        "indices": [],
        "foreignKeys": []
      }
    ],
    "views": [],
    "setupQueries": [
      "CREATE TABLE IF NOT EXISTS room_master_table (id INTEGER PRIMARY KEY,identity_hash TEXT)",
      "INSERT OR REPLACE INTO room_master_table (id,identity_hash) VALUES(42, '2d709ab1dff06d0c8193ccd413a3d2b9')"
    ]
  }
}